jsonrpc_pyclient/__init__.py
jsonrpc_pyclient/batch.py
jsonrpc_pyclient/client.py
jsonrpc_pyclient/error.py
jsonrpc_pyclient/protocolhandler.py
jsonrpc_pyclient/connectors/__init__.py
jsonrpc_pyclient/connectors/httpclient.py
jsonrpc_pyclient/connectors/socketclient.py
jsonrpc_pyclient-1.1.3.dist-info/DESCRIPTION.rst
jsonrpc_pyclient-1.1.3.dist-info/METADATA
jsonrpc_pyclient-1.1.3.dist-info/RECORD
jsonrpc_pyclient-1.1.3.dist-info/WHEEL
jsonrpc_pyclient-1.1.3.dist-info/metadata.json
jsonrpc_pyclient-1.1.3.dist-info/top_level.txt
tests/dummyservers/__init__.py
tests/dummyservers/httpserver.py
tests/dummyservers/socketserver.py
