Metadata-Version: 2.0
Name: jsonrpc-pyclient
Version: 1.1.3
Summary: A transport-agnostic json-rpc client library
Home-page: https://github.com/tvannoy/jsonrpc_pyclient
Author: Trevor Vannoy
Author-email: trevor.vannoy@flukecal.com
License: MIT
Keywords: rpc json json-rpc
Platform: UNKNOWN
Classifier: Development Status :: 4 - Beta
Classifier: License :: OSI Approved :: MIT License
Classifier: Programming Language :: Python :: 2
Classifier: Programming Language :: Python :: 3
Requires-Dist: requests
Provides-Extra: test
Requires-Dist: werkzeug; extra == 'test'
